{
  "공통": {
    "공통": {
      "이전": "前",
      "시작하기": "入门",
      "확인": "查看",
      "실행": "执行"
    }
  },
  "홈": {
    "이용가이드": {
      "이용가이드": "用户指南"
    },
    "다국어": {
      "Language": "Language",
      "한국어": "한국어",
      "ENGLISH": "ENGLISH",
      "日本語": "日本語",
      "繁體中文": "繁體中文",
      "简体中文": "简体中文",
      "PRINT YOUR PHOTOCARD": "PRINT YOUR PHOTOCARD",
      "PRINT YOUR MOMENT": "PRINT YOUR MOMENT",
      "SAYCHEEZ": "SAYCHEEZ"
    },
    "매장명": {
      "{{매장명}}": "{{商店名称}}"
    },
    "매장명 로딩": {
      "새로고침": "刷新",
      "장소를 불러오지 못했어요. 다시 시도해주세요.": "无法加载位置信息，请重试。",
      "장소를 불러오는 중이에요.": "正在加载位置。"
    },
    "오류/에러코드": {
      "키오스크에 문제가 발생했어요": "自助服务终端有问题。",
      "에러코드 발생: [{{error-code}}]": "出现错误代码：[{{error-code}}]",
      "매장 관리자에게 문의해주세요.": "请联系店长。",
      "키오스크를 사용하실 수 없어요": "我无法使用自助服务终端。"
    },
    "오류/리본부족": {
      "현재 키오스크에 리본이 부족해요.": "我们自助服务终端的色带快用完了。"
    },
    "오류/필름부족": {
      "현재 키오스크에 필름이 부족해요.": "我们自助服务亭的胶卷快用完了。"
    },
    "오류/카드부족": {
      "현재 키오스크에 카드가 부족해요.": "自助服务亭目前没有卡了。"
    }
  },
  "관리자모드": {
    "관리자 모드": {
      "관리자 모드": "管理员模式",
      "프린트 서버 재시작": "重启打印服务器",
      "키오스크가 정상적으로 작동하지 않는다면 서버를 재시작 해주세요.": "如果自助服务终端无法正常工作，请重启服务器。",
      "프린트 상태 초기화": "重置打印状态",
      "프린트 점검 또는 부족한 재료 보충 후 프린트 상태를 초기화 해주세요.": "检查打印任务或补充不足的耗材后，请重置打印状态。",
      "테스트 프린트": "测试打印",
      "정상적인 프린트 결과를 확인하시려면 테스트 프린트를 실행해주세요.": "请运行测试打印以检查打印结果是否正常。",
      "서버 재시작을 완료했어요.": "服务器重启已完成。",
      "상태 초기화를 완료했어요.": "状态初始化完成。",
      "테스트 프린트를 완료했어요.": "我完成了测试打印。"
    }
  },
  "하드웨어QR코드": {
    "QR코드": {
      "세이치즈 앱에서 QR코드를 스캔해주세요": "请在Seicheese应用程序中扫描二维码。"
    },
    "5분 타이머": {
      "{{minute}}:{{second}}": "{{分钟}}:{{秒}}"
    },
    "인증번호": {
      "인증번호": "认证号码"
    },
    "PIN번호 6자리": {
      "{{random}}": "{{随机的}}"
    },
    "로딩": {
      "인증을 위해서 QR코드를 만들고 있어요": "我正在创建一个用于身份验证的二维码。",
      "잠시만 기다려 주세요.": "请稍等片刻。"
    },
    "에러": {
      "QR코드 로딩에 실패했어요": "二维码加载失败",
      "새로고침을 눌러 다시 시도해주세요.": "请按刷新键重试。"
    }
  },
  "하드웨어 이용 가이드": {
    "이용 가이드": {
      "세이치즈 이용가이드": "SAYCHEEZ 用户指南",
      "SAYCHEEZ 앱을 설치해주세요.": "请安装SAYCHEEZ应用程序。",
      "원하는 사진을 업로드해주세요.": "请上传您想要的照片。",
      "업로드한 사진을 포토카드로 출력해보세요.": "将上传的照片打印成照片卡片。"
    }
  },
  "하드웨어운세": {
    "하드웨어운세": {
      "운세 카드를 뒤집어라": "翻开你的幸运卡",
      "카드를 골라 오늘의 운세를 확인하세요!": "抽一张牌，看看你今天的运势吧！",
      "인증이 완료됐어요": "身份验证已完成",
      "프린트 정보를 전송 중이예요": "发送打印信息",
      "{{second}}초 후 자동으로 선택됩니다": "它将在 {{second}} 秒后自动选中。",
      "[{장소명}]에서 포토카드를 인쇄 중이에요": "在 [{location name}] 打印照片卡",
      "당신의 운세가 나왔어요!": "你的运势公布了！",
      "프린트가 완료되었어요": "打印完成",
      "프린트 오류": "打印错误",
      "현재 키오스크에서 오류가 발생했습니다.": "当前自助服务终端发生故障。"
    }
  },
  "하드웨어출력완료": {
    "하드웨어출력완료": {
      "포토카드 프린트를 완료했어요": "照片卡打印完了。",
      "하단에 포토카드를 찾아가주세요.": "请在底部查找照片卡。",
      "포토카드가 나왔어요!": "照片卡已经发售了！"
    }
  }
}